environ/__init__.py
environ/compat.py
environ/environ.py
django_environ_2-2.3.0.dist-info/LICENSE
django_environ_2-2.3.0.dist-info/METADATA
django_environ_2-2.3.0.dist-info/WHEEL
django_environ_2-2.3.0.dist-info/top_level.txt
django_environ_2-2.3.0.dist-info/RECORD
