Metadata-Version: 2.1
Name: django-environ-2
Version: 2.3.0
Summary: Configure Django made easy.
Home-page: https://django-environ-2.readthedocs.io
Author: Daniele Faraglia
Author-email: daniele.faraglia@gmail.com
Maintainer: Serghei Iakovlev
Maintainer-email: egrep@protonmail.ch
License: MIT
Project-URL: Documentation, https://django-environ-2.readthedocs.io
Project-URL: Changelog, https://django-environ-2.readthedocs.io/en/latest/changelog.html
Project-URL: Bug Tracker, https://github.com/sergeyklay/django-environ-2/issues
Project-URL: Source Code, https://github.com/sergeyklay/django-environ-2
Keywords: environment,django,variables,12factor
Platform: any
Classifier: Development Status :: 5 - Production/Stable
Classifier: Framework :: Django
Classifier: Framework :: Django :: 1.11
Classifier: Framework :: Django :: 2.0
Classifier: Framework :: Django :: 2.1
Classifier: Framework :: Django :: 2.2
Classifier: Framework :: Django :: 3.0
Classifier: Framework :: Django :: 3.1
Classifier: Framework :: Django :: 3.2
Classifier: Operating System :: OS Independent
Classifier: Intended Audience :: Developers
Classifier: Natural Language :: English
Classifier: Programming Language :: Python
Classifier: Programming Language :: Python :: 3
Classifier: Programming Language :: Python :: 3.6
Classifier: Programming Language :: Python :: 3.7
Classifier: Programming Language :: Python :: 3.8
Classifier: Programming Language :: Python :: 3.9
Classifier: Programming Language :: Python :: 3.10
Classifier: Programming Language :: Python :: Implementation :: CPython
Classifier: Programming Language :: Python :: Implementation :: PyPy
Classifier: Topic :: Software Development :: Libraries :: Python Modules
Classifier: Topic :: Utilities
Classifier: License :: OSI Approved :: MIT License
Requires-Python: >=3.6, <4
License-File: LICENSE
Requires-Dist: django-environ
Provides-Extra: develop
Requires-Dist: coverage[toml] (>=5.4) ; extra == 'develop'
Requires-Dist: pytest (>=6.2.4) ; extra == 'develop'
Requires-Dist: pylint (!=2.6.1,>=2.6.0) ; extra == 'develop'
Requires-Dist: flake8 (>=3.8.4) ; extra == 'develop'
Requires-Dist: flake8-import-order (>=0.18.1) ; extra == 'develop'
Requires-Dist: flake8-blind-except (>=0.2.0) ; extra == 'develop'
Requires-Dist: check-manifest (>=0.45) ; extra == 'develop'
Requires-Dist: furo (==2021.8.*,>=2021.8.17b43) ; extra == 'develop'
Requires-Dist: sphinx (>=3.5.0) ; extra == 'develop'
Requires-Dist: sphinx-notfound-page ; extra == 'develop'
Provides-Extra: docs
Requires-Dist: furo (==2021.8.*,>=2021.8.17b43) ; extra == 'docs'
Requires-Dist: sphinx (>=3.5.0) ; extra == 'docs'
Requires-Dist: sphinx-notfound-page ; extra == 'docs'
Provides-Extra: testing
Requires-Dist: coverage[toml] (>=5.4) ; extra == 'testing'
Requires-Dist: pytest (>=6.2.4) ; extra == 'testing'
Requires-Dist: pylint (!=2.6.1,>=2.6.0) ; extra == 'testing'
Requires-Dist: flake8 (>=3.8.4) ; extra == 'testing'
Requires-Dist: flake8-import-order (>=0.18.1) ; extra == 'testing'
Requires-Dist: flake8-blind-except (>=0.2.0) ; extra == 'testing'
Requires-Dist: check-manifest (>=0.45) ; extra == 'testing'
